devpayr/__init__.py
devpayr/devpayr.py
devpayr/config/__init__.py
devpayr/config/config.py
devpayr/contracts/__init__.py
devpayr/contracts/injectable_processor.py
devpayr/crypto/__init__.py
devpayr/crypto/crypto_helper.py
devpayr/crypto/hash_helper.py
devpayr/exceptions/__init__.py
devpayr/exceptions/exceptions.py
devpayr/http/__init__.py
devpayr/http/http_client.py
devpayr/runtime/__init__.py
devpayr/runtime/validator.py
devpayr/services/__init__.py
devpayr/services/domain_service.py
devpayr/services/injectable_service.py
devpayr/services/license_service.py
devpayr/services/payment_service.py
devpayr/services/project_service.py
devpayr/support/__init__.py
devpayr/support/injectable_handler.py
devpayr_python_sdk-0.1.2.dist-info/licenses/LICENSE
devpayr_python_sdk-0.1.2.dist-info/METADATA
devpayr_python_sdk-0.1.2.dist-info/WHEEL
devpayr_python_sdk-0.1.2.dist-info/top_level.txt
devpayr_python_sdk-0.1.2.dist-info/RECORD
