Metadata-Version: 2.4
Name: devpayr-python-sdk
Version: 0.1.2
Summary: Framework-agnostic Python SDK for DevPayr – License enforcement, injectables, project & license management
Home-page: https://github.com/Xultech-LTD/devpayr_python_sdk
Author: XulTech
Author-email: XulTech <support@devpayr.com>
License: MIT License
Project-URL: Homepage, https://devpayr.com
Project-URL: Documentation, https://docs.devpayr.com
Project-URL: Repository, https://github.com/Xultech-LTD/devpayr_python_sdk
Project-URL: Issues, https://github.com/Xultech-LTD/devpayr_python_sdk/issues
Keywords: DevPayr,license,sdk,license-key,injectables,api-client,saas,encryption,project-management,framework-agnostic
Classifier: Development Status :: 3 - Alpha
Classifier: Intended Audience :: Developers
Classifier: License :: OSI Approved :: MIT License
Classifier: Programming Language :: Python :: 3
Classifier: Programming Language :: Python :: 3.7
Classifier: Programming Language :: Python :: 3.8
Classifier: Programming Language :: Python :: 3.9
Classifier: Programming Language :: Python :: 3.10
Classifier: Programming Language :: Python :: 3.11
Classifier: Topic :: Software Development :: Libraries
Classifier: Topic :: Software Development :: Build Tools
Requires-Python: >=3.7
License-File: LICENSE
Dynamic: author
Dynamic: home-page
Dynamic: license-file
Dynamic: requires-python
